postcodes_uk/__init__.py
postcodes_uk/version.py
postcodes_uk/main/__init__.py
postcodes_uk/main/exceptions.py
postcodes_uk/main/formatter.py
postcodes_uk/main/validator.py
postcodes_uk/tests/__init__.py
postcodes_uk/tests/test_formatter.py
postcodes_uk/tests/test_validator.py
uk_postcodes/__init__.py
uk_postcodes/version.py
uk_postcodes/main/__init__.py
uk_postcodes/main/exceptions.py
uk_postcodes/main/formatter.py
uk_postcodes/main/validator.py
uk_postcodes/tests/__init__.py
uk_postcodes/tests/test_formatter.py
uk_postcodes/tests/test_validator.py
postcodes_uk-1.0.2.dist-info/METADATA
postcodes_uk-1.0.2.dist-info/WHEEL
postcodes_uk-1.0.2.dist-info/top_level.txt
postcodes_uk-1.0.2.dist-info/RECORD
