Metadata-Version: 2.1
Name: postcodes-uk
Version: 1.0.2
Summary: Validate and format UK postcodes.
Home-page: https://github.com/marco-cardoso/uk_postcodes
Author: Marco Cardoso
Author-email: marco.carddoso.2020@gmail.com
License: BSD 3
Platform: UNKNOWN
Classifier: License :: OSI Approved :: MIT License
Classifier: Programming Language :: Python
Classifier: Programming Language :: Python :: 3
Classifier: Programming Language :: Python :: 3.6
Classifier: Programming Language :: Python :: 3.7
Classifier: Programming Language :: Python :: 3.8
Classifier: Programming Language :: Python :: Implementation :: CPython
Classifier: Programming Language :: Python :: Implementation :: PyPy
Requires-Python: >=3.6.0
Requires-Dist: pytest (==5.4.3)
